dicegame/__init__.py
dicegame/__main__.py
dicegame/add.py
dicegame/cmdline.py
tests/__init__.py
tests/test_add.py
tests/test_cmdline.py
dicegame-0.1.6.dist-info/LICENSE
dicegame-0.1.6.dist-info/METADATA
dicegame-0.1.6.dist-info/WHEEL
dicegame-0.1.6.dist-info/entry_points.txt
dicegame-0.1.6.dist-info/top_level.txt
dicegame-0.1.6.dist-info/RECORD
