Metadata-Version: 2.1
Name: dicegame
Version: 0.1.6
License-File: LICENSE
